{
    "definicoes_regulares": {
        "digito": "0123456789", 
        "letra": "abcdefghijklmnopqrstuvwxyzABCDEFGHIJKLMNOPQRSTUVWXYZ",
        "linha": " \t\n",
        "letradigito_": "0123456789abcdefghijklmnopqrstuvwxyzABCDEFGHIJKLMNOPQRSTUVWXYZ_",
        "letradigito": "0123456789abcdefghijklmnopqrstuvwxyzABCDEFGHIJKLMNOPQRSTUVWXYZ",
        "fracao": "E",

        "^digito.E": " !\"#$%&'()}*+,-/:;<=>?@ABCDFGHIJKLMNOPQRSTUVWXYZ[\\]^_`abcdefghijklmnopqrstuvwxyz{|~\t\n\r",
        "^digito": " !\"#$%&'()*+,-./}:;<=>?@ABCDEFGHIJKLMNOPQRSTUVWXYZ[\\]^_`abcdefghijklmnopqrstuvwxyz{|~\t\n\r",
        "^letradigito_": " !\"#$%&'()*+,-./:;<=>?@[\\]^`{|}~\t\n\r",
        "^linha": "!\"#$%&'()*+,-./0123456789:;<=>?@ABCDEFGHIJKLMNOPQRSTUVWXYZ[\\]^_`abcdefghijklmnopqrstuvwxyz{|}~\r",
        "^bracket": " !\"#$%&'()*+,-./0123456789:;<=>?@ABCDEFGHIJKLMNOPQRSTUVWXYZ[\\]^_`abcdefghijklmnopqrstuvwxyz{|~\t\n\r",
        "^equal": " !\"#$%&'()*+,-./0123456789:;<>?@ABCDEFGHIJKLMNOPQRSTUVWXYZ[\\]^_`abcdefghijklmnopqrstuvwxyz{|}~\t\n\r",
        "^fracao": " !\"#$%&'()*+,-/:;<=>?@ABCDFGHIJKLMNOPQRSTUVWXYZ[\\]^_`abcdefghijklmnopqrstuvwxyz{|}~\t\n\r"
    },

    "inicial": "0",

    "finais":{
        "9": ["program", "None"], 
        "16": ["begin", "None"], 
        "21": ["end", "None"], 
        "25": ["if", "None"], 
        "31": ["else", "None"], 
        "37": ["then", "None"], 
        "41": ["then", "teste"], 
        "45": ["then", "teste"], 
        "52": ["while", "None"], 
        "60": ["repeat", "None"], 
        "67": ["until", "None"], 
        "71": ["id", "None"], 
        "77": ["GT", "None"], 
        "78": ["GE", "None"], 
        "79": ["NE", "None"], 
        "80": ["LE", "None"], 
        "81": ["LT", "None"], 
        "86": ["type", "int"], 
        "91": ["type", "char"], 
        "97": ["type", "float"], 
        "101": ["constant_int", "None"], 
        "104": ["constant_char", "None"], 
        "110": ["constant_float", "None"], 
        "112": ["constant_float", "None"], 
        "114": ["left_parent", "None"],
        "116": ["right_parent", "None"], 
        "118": [";", "None"], 
        "120": [":", "None"], 
        "122": ["+", "None"], 
        "124": ["-", "None"], 
        "126": ["*", "None"], 
        "128": ["/", "None"], 
        "130": ["^", "None"], 
        "133": [":=", "None"]
        

    },

    "transicoes": [
        ["0","114","("],  ["0","116",")"], ["0","118",";"],
        ["0","120",":"], ["0","122","+"], ["0","124","-"],
        ["0","126","*"], ["0","128","/"], ["0","130","^"],
        ["0","2","p"], ["0","e","e"], ["0","54","r"], 
        ["0","62","u"], ["0","87","c"],
        ["0","69","acdfghjklmnoqsvxyzACDFGHJKLMNOQSVXYZ"],
        ["0","39","linha"], ["0","43","{"], ["0","47","w"],
        ["0","33","t"], ["0","92","f"], ["0","73",">"],
        ["0","74","="], ["0","75","!"], ["0","76","<"],
        ["0","11","b"], ["0","i","i"], ["0","99","+-"],
        ["0","dig","letra"], ["0","103","\""], ["0","132",":"],
            
        ["2","3","r"], ["3","4","o"], ["4","5","g"],
        ["5","6","r"], ["6","7","a"], ["7","8","m"],
        ["8","9","^letra digito _"], ["8","69","letra digito _"],
        ["69","70","letra digito _"], ["70","71","^letra digito _"],

        ["e","28","l"], ["28","29","s"], ["29","30","e"], 
        ["30","31","^letra digito _"], ["30","69","letra digito _"], ["e","19","g"], 
        ["19","20","g"], ["20","21","^letra digito _"], ["20","69","letra digito _"],

        ["54","55","e"], ["55","56","p"], ["56","57","e"], 
        ["57","58","a"], ["58","59","t"], ["59","60","^letra digito _"], ["59","69","letra digito _"],

        ["62","63","n"], ["63","64","t"], ["64","65","i"], 
        ["65","66","l"], ["66","67","^letra digito _"], ["66","69","letra digito _"], 

        ["87","88","h"], ["88","89","a"], ["89","90","r"], 
        ["90","91","^letra digito _"], ["90","69","letra digito _"],

        ["39","40","linha"], ["40","41","^linha"], 
        ["43","44","bracket"], ["44","45","}"], 
        
        ["47","48","h"], ["48","49","i"], ["49","50","l"], 
        ["50","51","e"], ["51","52","^letra digito _"], ["51","69","letra digito _"], 
        
        ["33","34","h"], ["34","35","e"], ["35","36","n"], 
        ["36","37","^letra digito _"], ["36","69","letra digito _"], 
        
        ["92","93","l"], ["93","94","o"], ["94","95","a"], 
        ["95","96","t"], ["96","97","^letra digito _"], ["97","69","letra digito _"], 

        ["73","77","^equal"], ["73","78","="],["75","79","="], 
        ["76","80","="], ["76","81","^equal"],

        ["11","12","e"], ["12","13","g"], ["13","14","i"], 
        ["14","15","n"], ["15","16","^letra digito _"], ["15","69","letra digito _"], 
        
        ["i","24","f"], ["24","25","^letra digito _"], ["24","69","letra digito _"], 
        ["i","84","n"], ["84","85","t"], 
        ["85","86","^letra digito _"], ["85","69","letra digito _"], 
        
        ["99","dig","e"], ["dig","101","^digito"], ["dig","107","."], 
        ["107","108","digito"], ["108","108","digito"], ["108","112","^fracao"],
        ["108","109","fracao"], ["109","109","+-"], ["109","110","digito"],["110","110","digito"],

        ["103","103","letra digito"], ["103","104","'"], 
        ["132","133","="]
    

    ],

    "lookaheads": ["9", "16", "21", "25", "31", "37", "41", "52", 
    "60", "67", "71", "77", "81", "86", "91", "97", 
    "101", "104", "110", "112", "114", "116", "118", "120", "122", "124", 
    "126", "128", "130"]
}